{
    "Ar36": {
        "error": 0.00011012990471354193,
        "error_type": "SEM",
        "filter_outliers_dict": {
            "filter_outliers": true,
            "iterations": 1,
            "std_devs": 3,
            "use_iqr_filtering": false,
            "use_standard_deviation_filtering": false
        },
        "fit": "linear",
        "fn": 396,
        "include_baseline_error": true,
        "n": 400,
        "outlier_excluded": [
            341,
            261,
            302,
            335
        ],
        "reviewed": true,
        "user_excluded": [],
        "value": 0.0019067917142015839
    },
    "Ar37": {
        "error": 0.012589397874825041,
        "error_type": "SEM",
        "filter_outliers_dict": {
            "filter_outliers": true,
            "iterations": 1,
            "std_devs": 3,
            "use_iqr_filtering": false,
            "use_standard_deviation_filtering": false
        },
        "fit": "linear",
        "fn": 397,
        "include_baseline_error": true,
        "n": 400,
        "outlier_excluded": [
            306,
            398,
            375
        ],
        "reviewed": true,
        "user_excluded": [],
        "value": -0.19284812786915057
    },
    "Ar38": {
        "error": 0.0048519895311678945,
        "error_type": "SEM",
        "filter_outliers_dict": {
            "filter_outliers": true,
            "iterations": 1,
            "std_devs": 3,
            "use_iqr_filtering": false,
            "use_standard_deviation_filtering": false
        },
        "fit": "linear",
        "fn": 399,
        "include_baseline_error": true,
        "n": 400,
        "outlier_excluded": [
            109
        ],
        "reviewed": true,
        "user_excluded": [],
        "value": -0.06188794824372665
    },
    "Ar39": {
        "error": 0.01663505428050166,
        "error_type": "SEM",
        "filter_outliers_dict": {
            "filter_outliers": true,
            "iterations": 1,
            "std_devs": 3,
            "use_iqr_filtering": false,
            "use_standard_deviation_filtering": false
        },
        "fit": "linear",
        "fn": 400,
        "include_baseline_error": true,
        "n": 400,
        "outlier_excluded": [],
        "reviewed": true,
        "user_excluded": [],
        "value": -0.025136540678554718
    },
    "Ar40": {
        "error": 0.02427975487444946,
        "error_type": "SEM",
        "filter_outliers_dict": {
            "filter_outliers": true,
            "iterations": 1,
            "std_devs": 3,
            "use_iqr_filtering": false,
            "use_standard_deviation_filtering": false
        },
        "fit": "parabolic",
        "fn": 399,
        "include_baseline_error": true,
        "n": 400,
        "outlier_excluded": [
            132
        ],
        "reviewed": true,
        "user_excluded": [],
        "value": 0.097205480492611
    }
}