{
    "Ar36": {
        "error": 0.006588552469388759,
        "error_type": "SEM",
        "filter_outliers_dict": {
            "filter_outliers": true,
            "iterations": 1,
            "std_devs": 2
        },
        "fit": "Parabolic",
        "fn": 328,
        "include_baseline_error": false,
        "n": 340,
        "reviewed": true,
        "value": 5.526191809636186
    },
    "Ar37": {
        "error": 0.012685362360521738,
        "error_type": "SEM",
        "filter_outliers_dict": {
            "filter_outliers": true,
            "iterations": 1,
            "std_devs": 2
        },
        "fit": "Linear",
        "fn": 322,
        "include_baseline_error": false,
        "n": 340,
        "reviewed": true,
        "value": -0.3230097441281879
    },
    "Ar38": {
        "error": 0.004974387064198154,
        "error_type": "SEM",
        "filter_outliers_dict": {
            "filter_outliers": true,
            "iterations": 1,
            "std_devs": 2
        },
        "fit": "Linear",
        "fn": 326,
        "include_baseline_error": false,
        "n": 340,
        "reviewed": true,
        "value": 1.0073655865119169
    },
    "Ar39": {
        "error": 0.0306862096973964,
        "error_type": "SEM",
        "filter_outliers_dict": {
            "filter_outliers": true,
            "iterations": 1,
            "std_devs": 2
        },
        "fit": "Parabolic",
        "fn": 326,
        "include_baseline_error": false,
        "n": 340,
        "reviewed": true,
        "value": -0.030897427762430058
    },
    "Ar40": {
        "error": 0.11566361130056724,
        "error_type": "SEM",
        "filter_outliers_dict": {
            "filter_outliers": true,
            "iterations": 1,
            "std_devs": 2
        },
        "fit": "Parabolic",
        "fn": 324,
        "include_baseline_error": false,
        "n": 340,
        "reviewed": true,
        "value": 1698.0113048400322
    }
}